{
    "variants": {
        "enabled=false,facing=east":  { "model": "thaumcraft:block/pattern_crafter", "y": 90 },
        "enabled=false,facing=west":  { "model": "thaumcraft:block/pattern_crafter", "y": 270 },
        "enabled=false,facing=north": { "model": "thaumcraft:block/pattern_crafter" },
        "enabled=false,facing=south": { "model": "thaumcraft:block/pattern_crafter", "y": 180 },
        "enabled=true,facing=east":   { "model": "thaumcraft:block/pattern_crafter_on", "y": 90 },
        "enabled=true,facing=west":   { "model": "thaumcraft:block/pattern_crafter_on", "y": 270 },
        "enabled=true,facing=north":  { "model": "thaumcraft:block/pattern_crafter_on" },
        "enabled=true,facing=south":  { "model": "thaumcraft:block/pattern_crafter_on", "y": 180 }
    }
}
